data/__init__.py
data/aisnps/__init__.py
data/aisnps/custom.aisnp.txt
data/aisnps/kidd.1kG.csv
data/aisnps/kidd.aisnp.1kg.vcf
data/aisnps/kidd.aisnp.hg38.txt
data/aisnps/kidd.aisnp.txt
data/aisnps/seldin.1kG.csv
data/aisnps/seldin.aisnp.1kg.vcf
data/aisnps/seldin.aisnp.hg38.txt
data/aisnps/seldin.aisnp.txt
data/models/__init__.py
data/models/kidd_population.pkl
data/models/kidd_superpopulation.pkl
data/models/seldin_population.pkl
data/models/seldin_superpopulation.pkl
ezancestry/__init__.py
ezancestry/commands.py
ezancestry/config.py
ezancestry/evaluate.py
ezancestry/fetch.py
ezancestry/model.py
ezancestry/process.py
ezancestry-0.1.0.dist-info/LICENSE
ezancestry-0.1.0.dist-info/METADATA
ezancestry-0.1.0.dist-info/WHEEL
ezancestry-0.1.0.dist-info/entry_points.txt
ezancestry-0.1.0.dist-info/RECORD
