Metadata-Version: 2.1
Name: ezancestry
Version: 0.1.0
Summary: Easily predict and visualize genetic ancestry. Evaluate custom ancestry-informative SNP sets.
License: MIT
Keywords: ancestry,genetics,bioinformatics,machine learning
Author: arvkevi
Author-email: arvkevi@gmail.com
Requires-Python: >=3.8,<3.12
Classifier: License :: OSI Approved :: MIT License
Classifier: Programming Language :: Python :: 3
Classifier: Programming Language :: Python :: 3.8
Classifier: Programming Language :: Python :: 3.9
Classifier: Programming Language :: Python :: 3.10
Classifier: Programming Language :: Python :: 3.11
Requires-Dist: loguru (>=0.5.3,<0.6.0)
Requires-Dist: numpy (>=1.21.2,<2.0.0)
Requires-Dist: pandas (>=1.3.2,<2.0.0)
Requires-Dist: plotly (>=5.3.1)
Requires-Dist: pysam (>=0.22.0,<0.23.0)
Requires-Dist: scikit-learn (>=1.0.1)
Requires-Dist: snps (>=2.3.0)
Requires-Dist: typer (>=0.8.0)
